LICENSE
MANIFEST.in
README.md
setup.py
spleeter/__init__.py
spleeter/__main__.py
spleeter/dataset.py
spleeter/separator.py
spleeter/audio/__init__.py
spleeter/audio/adapter.py
spleeter/audio/convertor.py
spleeter/audio/ffmpeg.py
spleeter/audio/spectrogram.py
spleeter/commands/__init__.py
spleeter/commands/evaluate.py
spleeter/commands/separate.py
spleeter/commands/train.py
spleeter/model/__init__.py
spleeter/model/functions/__init__.py
spleeter/model/functions/blstm.py
spleeter/model/functions/unet.py
spleeter/model/provider/__init__.py
spleeter/model/provider/github.py
spleeter/resources/2stems-16kHz.json
spleeter/resources/2stems.json
spleeter/resources/4stems-16kHz.json
spleeter/resources/4stems.json
spleeter/resources/5stems-16kHz.json
spleeter/resources/5stems.json
spleeter/resources/__init__.py
spleeter/resources/musdb.json
spleeter/utils/__init__.py
spleeter/utils/configuration.py
spleeter/utils/estimator.py
spleeter/utils/logging.py
spleeter/utils/tensor.py
spleeter_gpu.egg-info/PKG-INFO
spleeter_gpu.egg-info/SOURCES.txt
spleeter_gpu.egg-info/dependency_links.txt
spleeter_gpu.egg-info/entry_points.txt
spleeter_gpu.egg-info/requires.txt
spleeter_gpu.egg-info/top_level.txt